MANIFEST.in
README.rst
setup.py
aio/__init__.py
aio.web.server.egg-info/PKG-INFO
aio.web.server.egg-info/SOURCES.txt
aio.web.server.egg-info/dependency_links.txt
aio.web.server.egg-info/namespace_packages.txt
aio.web.server.egg-info/not-zip-safe
aio.web.server.egg-info/requires.txt
aio.web.server.egg-info/top_level.txt
aio/web/__init__.py
aio/web/server/README.rst
aio/web/server/__init__.py
aio/web/server/aio.conf
aio/web/server/cmd.py
aio/web/server/factories.py
aio/web/server/fragments.py
aio/web/server/routes.py
aio/web/server/utils.py
aio/web/server/ws.py
aio/web/server/testing/__init__.py
aio/web/server/tests/__init__.py
aio/web/server/tests/test_factories.py
aio/web/server/tests/test_web_server.py
aio/web/server/tests/templates/test_template.html
aio/web/server/tests/templates/fragments/test_fragment.html